{
  "kind": "singleType",
  "collectionName": "footers",
  "info": {
    "singularName": "footer",
    "pluralName": "footers",
    "displayName": "Layout - Footer",
    "description": ""
  },
  "options": {
    "draftAndPublish": true
  },
  "pluginOptions": {
    "i18n": {
      "localized": true
    }
  },
  "attributes": {
    "text": {
      "pluginOptions": {
        "i18n": {
          "localized": true
        }
      },
      "type": "blocks"
    },
    "policyLinks": {
      "type": "component",
      "repeatable": true,
      "pluginOptions": {
        "i18n": {
          "localized": true
        }
      },
      "component": "elements.link"
    },
    "socialLinks": {
      "type": "component",
      "repeatable": true,
      "pluginOptions": {
        "i18n": {
          "localized": true
        }
      },
      "component": "elements.link"
    },
    "newsletterTitle": {
      "pluginOptions": {
        "i18n": {
          "localized": true
        }
      },
      "type": "string"
    },
    "logo": {
      "type": "component",
      "repeatable": false,
      "pluginOptions": {
        "i18n": {
          "localized": true
        }
      },
      "component": "elements.image"
    },
    "copyright": {
      "pluginOptions": {
        "i18n": {
          "localized": true
        }
      },
      "type": "blocks"
    }
  }
}
